Metadata-Version: 1.0
Name: lujing-distributions
Version: 0.1.1
Summary: Gaussian distributions
Home-page: UNKNOWN
Author: Lujing Yang
Author-email: lujing@me.com
License: UNKNOWN
Platform: UNKNOWN
